{
  "updated": "2026-06-12T13:00:02Z",
  "lake_level": 659.0,
  "full_pool": 660.0,
  "below_full_pool": 1.0,
  "water_temp_f": 78,
  "osage_temp_f": 73.8,
  "air_temp_f": 69,
  "feels_like_f": 73,
  "humidity": 91,
  "wind_speed_mph": 3,
  "wind_gusts_mph": 9,
  "wind_dir": "NNW",
  "wind_deg": 348,
  "weather_code": 0,
  "forecast": [
    {
      "date": "2026-06-12",
      "high_f": 85,
      "low_f": 68,
      "wind_max_mph": 4,
      "precip_in": 0.0,
      "weather_code": 0
    },
    {
      "date": "2026-06-13",
      "high_f": 90,
      "low_f": 65,
      "wind_max_mph": 16,
      "precip_in": 3.737,
      "weather_code": 0
    },
    {
      "date": "2026-06-14",
      "high_f": 73,
      "low_f": 60,
      "wind_max_mph": 10,
      "precip_in": 0.039,
      "weather_code": 0
    }
  ]
}